setup.py
ka_in_st/__init__.py
ka_in_st/asgi.py
ka_in_st/settings.py
ka_in_st/urls.py
ka_in_st/wsgi.py
ka_in_st.egg-info/PKG-INFO
ka_in_st.egg-info/SOURCES.txt
ka_in_st.egg-info/dependency_links.txt
ka_in_st.egg-info/requires.txt
ka_in_st.egg-info/top_level.txt
st/__init__.py
st/admin.py
st/apps.py
st/fields.py
st/forms.py
st/models.py
st/states.py
st/tests.py
st/views.py
st/migrations/__init__.py