Metadata-Version: 2.1
Name: ka-in-st
Version: 0.1
Summary: A Django app that provides Indian state choices as a model and form field.
Author: Kamal Sir
Author-email: kamalsir@ymail.com
License: MIT
Classifier: Framework :: Django
Classifier: Programming Language :: Python :: 3
